torchaddons/__init__.py
torchaddons/distributions/__init__.py
torchaddons/distributions/_base.py
torchaddons/distributions/_categorical.py
torchaddons/distributions/_normal.py
torchaddons/distributions/_rejection_sampler.py
torchaddons/distributions/constraints/__init__.py
torchaddons/distributions/constraints/_base.py
torchaddons/distributions/constraints/_categorical_mask.py
torchaddons/distributions/constraints/_empty.py
torchaddons/distributions/constraints/_lower_bound.py
torchaddons/distributions/constraints/_upper_bound.py
torchaddons/random/__init__.py
torchaddons/random/_choice.py
torchaddons_jks-0.0.7.dist-info/LICENSE
torchaddons_jks-0.0.7.dist-info/METADATA
torchaddons_jks-0.0.7.dist-info/WHEEL
torchaddons_jks-0.0.7.dist-info/top_level.txt
torchaddons_jks-0.0.7.dist-info/RECORD
