Metadata-Version: 2.1
Name: torchaddons-jks
Version: 0.0.7
Summary: Addons for torch.
Home-page: https://github.com/jakkes/torchaddons
Author: Jakob Stigenberg
Author-email: jakob@jakke.se
License: UNKNOWN
Project-URL: Bug Tracker, https://github.com/jakkes/torchaddons/issues
Platform: UNKNOWN
Classifier: Programming Language :: Python :: 3
Classifier: License :: OSI Approved :: MIT License
Classifier: Operating System :: OS Independent
Requires-Python: >=3.8
License-File: LICENSE
Requires-Dist: torch (~=1.10)
Requires-Dist: numpy (~=1.22)
